oboron-0.1.0.dist-info/METADATA
oboron-0.1.0.dist-info/WHEEL
oboron/__init__.py
oboron/_oboron.cpython-310-x86_64-linux-gnu.so
oboron/formats.py
oboron/keygen.py
oboron/test_inheritance.py
oboron/ztier.py
oboron-0.1.0.dist-info/RECORD
