Metadata-Version: 2.4
Name: oboron
Version: 0.1.0
Classifier: Development Status :: 4 - Beta
Classifier: Intended Audience :: Developers
Classifier: License :: OSI Approved :: MIT License
Classifier: Operating System :: OS Independent
Classifier: Programming Language :: Python :: 3
Classifier: Programming Language :: Python :: 3.8
Classifier: Programming Language :: Python :: 3.9
Classifier: Programming Language :: Python :: 3.10
Classifier: Programming Language :: Python :: 3.11
Classifier: Programming Language :: Python :: 3.12
Classifier: Programming Language :: Rust
Classifier: Programming Language :: Python :: Implementation :: CPython
Classifier: Programming Language :: Python :: Implementation :: PyPy
Classifier: Topic :: Security :: Cryptography
Classifier: Topic :: Software Development :: Libraries :: Python Modules
Classifier: Typing :: Typed
Summary: Python bindings for Oboron - general purpose encryption and encoding library
Keywords: python,encryption,obfuscation,encoding,base32
Author: Bojan Đuričković
License: MIT
Requires-Python: >=3.8
Project-URL: Homepage, https://www.oboron.org/
Project-URL: Repository, https://github.com/grkteam/oboron-rs
Project-URL: Documentation, https://www.oboron.org/
